terminalcolorlog_pkg/LogOut.py
terminalcolorlog_pkg/__init__.py
TerminalColorLog-1.0.0b5.dist-info/LICENSE
TerminalColorLog-1.0.0b5.dist-info/METADATA
TerminalColorLog-1.0.0b5.dist-info/WHEEL
TerminalColorLog-1.0.0b5.dist-info/top_level.txt
TerminalColorLog-1.0.0b5.dist-info/RECORD
