Metadata-Version: 2.1
Name: TerminalColorLog
Version: 1.0.0b5
Summary: Print Have Color 's Log For Terminal 
Home-page: https://chenjj100419.github.io/WebBlogHtml
Author: chenjj100419
Author-email: 2026159790@qq.com
License: General Public License v3
Platform: any
Requires-Python: >=3.6
Requires-Dist: colorama
